{
    "$schema": "http://json-schema.org/draft-07/schema",
    "$id": "http://example.com/example.json",
    "type": "object",
    "title": "The root schema",
    "description": "The root schema comprises the entire JSON document.",
    "default": {},
    "examples": [
        {
            "code": 1,
            "message": "success",
            "data": {
                "access_key_id": "LTAI7MMCu3h4oaGD",
                "endpoint": "https://oss-ap-southeast-1.aliyuncs.com",
                "bucket_name": "fle-staging-asset-internal",
                "method": "PUT",
                "date": "Fri, 24 Jul 2020 04:41:01 GMT",
                "content_type": "image/jpeg",
                "signature": "Hl7Mmdx2XnvIJZMz0B2LcbRuuDg=",
                "object_key": "parcelManualImport/1595565661-02570d96fa5d4e3594b338b065ff09d8.jpg",
                "object_url": "https://fle-staging-asset-internal.oss-ap-southeast-1.aliyuncs.com/parcelManualImport/1595565661-02570d96fa5d4e3594b338b065ff09d8.jpg",
                "object_url_th": "https://fle-staging-asset-internal.oss-ap-southeast-1.aliyuncs.com/parcelManualImport/1595565661-02570d96fa5d4e3594b338b065ff09d8.jpg?x-oss-process=style/th",
                "object_url_x3": "https://fle-staging-asset-internal.oss-ap-southeast-1.aliyuncs.com/parcelManualImport/1595565661-02570d96fa5d4e3594b338b065ff09d8.jpg?x-oss-process=style/x3"
            }
        }
    ],
    "required": [
        "code",
        "message",
        "data"
    ],
    "properties": {
        "code": {
            "$id": "#/properties/code",
            "type": "integer",
            "title": "The code schema",
            "description": "An explanation about the purpose of this instance.",
            "default": 0,
            "examples": [
                1
            ]
        },
        "message": {
            "$id": "#/properties/message",
            "type": "string",
            "title": "The message schema",
            "description": "An explanation about the purpose of this instance.",
            "default": "",
            "examples": [
                "success"
            ]
        },
        "data": {
            "$id": "#/properties/data",
            "type": "object",
            "title": "The data schema",
            "description": "An explanation about the purpose of this instance.",
            "default": {},
            "examples": [
                {
                    "access_key_id": "LTAI7MMCu3h4oaGD",
                    "endpoint": "https://oss-ap-southeast-1.aliyuncs.com",
                    "bucket_name": "fle-staging-asset-internal",
                    "method": "PUT",
                    "date": "Fri, 24 Jul 2020 04:41:01 GMT",
                    "content_type": "image/jpeg",
                    "signature": "Hl7Mmdx2XnvIJZMz0B2LcbRuuDg=",
                    "object_key": "parcelManualImport/1595565661-02570d96fa5d4e3594b338b065ff09d8.jpg",
                    "object_url": "https://fle-staging-asset-internal.oss-ap-southeast-1.aliyuncs.com/parcelManualImport/1595565661-02570d96fa5d4e3594b338b065ff09d8.jpg",
                    "object_url_th": "https://fle-staging-asset-internal.oss-ap-southeast-1.aliyuncs.com/parcelManualImport/1595565661-02570d96fa5d4e3594b338b065ff09d8.jpg?x-oss-process=style/th",
                    "object_url_x3": "https://fle-staging-asset-internal.oss-ap-southeast-1.aliyuncs.com/parcelManualImport/1595565661-02570d96fa5d4e3594b338b065ff09d8.jpg?x-oss-process=style/x3"
                }
            ],
            "required": [
                "access_key_id",
                "endpoint",
                "bucket_name",
                "method",
                "date",
                "content_type",
                "signature",
                "object_key",
                "object_url",
                "object_url_th",
                "object_url_x3"
            ],
            "properties": {
                "access_key_id": {
                    "$id": "#/properties/data/properties/access_key_id",
                    "type": "string",
                    "title": "The access_key_id schema",
                    "description": "An explanation about the purpose of this instance.",
                    "default": "",
                    "examples": [
                        "LTAI7MMCu3h4oaGD"
                    ]
                },
                "endpoint": {
                    "$id": "#/properties/data/properties/endpoint",
                    "type": "string",
                    "title": "The endpoint schema",
                    "description": "An explanation about the purpose of this instance.",
                    "default": "",
                    "examples": [
                        "https://oss-ap-southeast-1.aliyuncs.com"
                    ]
                },
                "bucket_name": {
                    "$id": "#/properties/data/properties/bucket_name",
                    "type": "string",
                    "title": "The bucket_name schema",
                    "description": "An explanation about the purpose of this instance.",
                    "default": "",
                    "examples": [
                        "fle-staging-asset-internal"
                    ]
                },
                "method": {
                    "$id": "#/properties/data/properties/method",
                    "type": "string",
                    "title": "The method schema",
                    "description": "An explanation about the purpose of this instance.",
                    "default": "",
                    "examples": [
                        "PUT"
                    ]
                },
                "date": {
                    "$id": "#/properties/data/properties/date",
                    "type": "string",
                    "title": "The date schema",
                    "description": "An explanation about the purpose of this instance.",
                    "default": "",
                    "examples": [
                        "Fri, 24 Jul 2020 04:41:01 GMT"
                    ]
                },
                "content_type": {
                    "$id": "#/properties/data/properties/content_type",
                    "type": "string",
                    "title": "The content_type schema",
                    "description": "An explanation about the purpose of this instance.",
                    "default": "",
                    "examples": [
                        "image/jpeg"
                    ]
                },
                "signature": {
                    "$id": "#/properties/data/properties/signature",
                    "type": "string",
                    "title": "The signature schema",
                    "description": "An explanation about the purpose of this instance.",
                    "default": "",
                    "examples": [
                        "Hl7Mmdx2XnvIJZMz0B2LcbRuuDg="
                    ]
                },
                "object_key": {
                    "$id": "#/properties/data/properties/object_key",
                    "type": "string",
                    "title": "The object_key schema",
                    "description": "An explanation about the purpose of this instance.",
                    "default": "",
                    "examples": [
                        "parcelManualImport/1595565661-02570d96fa5d4e3594b338b065ff09d8.jpg"
                    ]
                },
                "object_url": {
                    "$id": "#/properties/data/properties/object_url",
                    "type": "string",
                    "title": "The object_url schema",
                    "description": "An explanation about the purpose of this instance.",
                    "default": "",
                    "examples": [
                        "https://fle-staging-asset-internal.oss-ap-southeast-1.aliyuncs.com/parcelManualImport/1595565661-02570d96fa5d4e3594b338b065ff09d8.jpg"
                    ]
                },
                "object_url_th": {
                    "$id": "#/properties/data/properties/object_url_th",
                    "type": "string",
                    "title": "The object_url_th schema",
                    "description": "An explanation about the purpose of this instance.",
                    "default": "",
                    "examples": [
                        "https://fle-staging-asset-internal.oss-ap-southeast-1.aliyuncs.com/parcelManualImport/1595565661-02570d96fa5d4e3594b338b065ff09d8.jpg?x-oss-process=style/th"
                    ]
                },
                "object_url_x3": {
                    "$id": "#/properties/data/properties/object_url_x3",
                    "type": "string",
                    "title": "The object_url_x3 schema",
                    "description": "An explanation about the purpose of this instance.",
                    "default": "",
                    "examples": [
                        "https://fle-staging-asset-internal.oss-ap-southeast-1.aliyuncs.com/parcelManualImport/1595565661-02570d96fa5d4e3594b338b065ff09d8.jpg?x-oss-process=style/x3"
                    ]
                }
            },
            "additionalProperties": true
        }
    },
    "additionalProperties": true
}